fsm-assignments/problem1_seqdet/seq_detect_mealy.v
module seq_detect_mealy(
    input  wire clk,
    input  wire rst,   // sync active-high reset
    input  wire din,
    output reg  y
);

    // State encoding with clear names
    parameter STATE_IDLE = 2'b00;   // no match
    parameter STATE_1    = 2'b01;   // matched "1"
    parameter STATE_11   = 2'b10;   // matched "11"
    parameter STATE_110  = 2'b11;   // matched "110"

    reg [1:0] state_present, state_next;

    // Next state logic + Mealy output
    always @(*) begin
        y = 0; // default
        case (state_present)
            STATE_IDLE: begin
                if (din) state_next = STATE_1;
                else     state_next = STATE_IDLE;
            end

            STATE_1: begin
                if (din) state_next = STATE_11;
                else     state_next = STATE_IDLE;
            end

            STATE_11: begin
                if (din) state_next = STATE_11;   // still "11"
                else     state_next = STATE_110;  // got "110"
            end

            STATE_110: begin
                if (din) begin
                    y = 1;                  // found "1101"
                    state_next = STATE_1;   // overlap (last bit = "1")
                end else begin
                    state_next = STATE_IDLE;
                end
            end

            default: state_next = STATE_IDLE;
        endcase
    end

    // State register (synchronous reset)
    always @(posedge clk) begin
        if (rst) begin
            state_present <= STATE_IDLE;
        end else begin
            state_present <= state_next;
        end
    end

endmodule

fsm-assignments/problem1_seqdet/tb_seq_detect_mealy.v
module tb_seq_detect_mealy;
    reg clk, rst, din;
    wire y;

  
    seq_detect_mealy dut (.clk(clk), .rst(rst), .din(din), .y(y));

    // Clock generation (100MHz -> 10ns period)
    always #5 clk = ~clk;

    initial begin
        $dumpfile("dump.vcd");
        $dumpvars(0, tb_seq_detect_mealy);

        // Initialize
        clk = 0; rst = 1; din = 0;
        #10; 
        rst = 0;

        // Test input stream: 11011011101
        repeat (1) begin
            din = 1; #10;
            din = 1; #10;
            din = 0; #10;
            din = 1; #10;
            din = 1; #10;
            din = 0; #10;
            din = 1; #10;
            din = 1; #10;
            din = 1; #10;
            din = 0; #10;
            din = 1; #10;
        end

        #20 $finish;
    end
endmodule

fsm-assignments/problem1_seqdet/waves/dump.vcd
$date
	Sun Aug 17 22:45:30 2025
$end
$version
	Icarus Verilog
$end
$timescale
	1s
$end
$scope module tb_seq_detect_mealy $end
$var wire 1 ! y $end
$var reg 1 " clk $end
$var reg 1 # din $end
$var reg 1 $ rst $end
$scope module dut $end
$var wire 1 " clk $end
$var wire 1 # din $end
$var wire 1 $ rst $end
$var parameter 2 % STATE_1 $end
$var parameter 2 & STATE_11 $end
$var parameter 2 ' STATE_110 $end
$var parameter 2 ( STATE_IDLE $end
$var reg 2 ) state_next [1:0] $end
$var reg 2 * state_present [1:0] $end
$var reg 1 ! y $end
$upscope $end
$upscope $end
$enddefinitions $end
$comment Show the parameter values. $end
$dumpall
b0 (
b11 '
b10 &
b1 %
$end
#0
$dumpvars
bx *
b0 )
1$
0#
0"
0!
$end
#5
b0 *
1"
#10
b1 )
0"
1#
0$
#15
b10 )
b1 *
1"
#20
0"
#25
b10 *
1"
#30
b11 )
0"
0#
#35
b0 )
b11 *
1"
#40
b1 )
1!
0"
1#
#45
b10 )
0!
b1 *
1"
#50
0"
#55
b10 *
1"
#60
b11 )
0"
0#
#65
b0 )
b11 *
1"
#70
b1 )
1!
0"
1#
#75
b10 )
0!
b1 *
1"
#80
0"
#85
b10 *
1"
#90
0"
#95
1"
#100
b11 )
0"
0#
#105
b0 )
b11 *
1"
#110
b1 )
1!
0"
1#
#115
b10 )
0!
b1 *
1"
#120
0"
#125
b10 *
1"
