problem3_vending/vending_mealy.v
module vending_mealy(
    input wire clk,
    input wire rst,       // synchronous, active-high
    input wire [1:0] coin, // 01=5, 10=10, 00=idle
    output reg dispense,  // 1-cycle pulse
    output reg chg5       // 1-cycle pulse
);

    // State encoding
    parameter S0=2'd0, S5=2'd1, S10=2'd2, S15=2'd3;
    reg [1:0] state, next_state;

    // Next-state logic and Mealy outputs
    always @(*) begin
        dispense = 0;
        chg5 = 0;
        case(state)
            S0: case(coin)
                    2'b01: next_state = S5;
                    2'b10: next_state = S10;
                    default: next_state = S0;
                 endcase
            S5: case(coin)
                    2'b01: next_state = S10;
                    2'b10: next_state = S15;
                    default: next_state = S5;
                 endcase
            S10: case(coin)
                    2'b01: next_state = S15;
                    2'b10: begin
                        next_state = S0;
                        dispense = 1;
                    end
                    default: next_state = S10;
                 endcase
            S15: case(coin)
                    2'b01: begin
                        next_state = S0;
                        dispense = 1;
                    end
                    2'b10: begin
                        next_state = S0;
                        dispense = 1;
                        chg5 = 1;
                    end
                    default: next_state = S15;
                 endcase
            default: next_state = S0;
        endcase
    end

    // State register
    always @(posedge clk) begin
        if(rst)
            state <= S0;
        else
            state <= next_state;
    end

endmodule

fsm-assignments/problem3_vending/tb_vending_mealy.v
`timescale 1ns/1ps

module tb_vending_mealy;
    reg clk, rst;
    reg [1:0] coin;
    wire dispense, chg5;

    // Instantiate DUT
    vending_mealy dut(
        .clk(clk),
        .rst(rst),
        .coin(coin),
        .dispense(dispense),
        .chg5(chg5)
    );

    // Clock
    initial clk = 0;
    always #5 clk = ~clk; // 10 ns period

    // VCD dump
    initial begin
        $dumpfile("vending.vcd");
        $dumpvars(0, tb_vending_mealy);
    end

    // Test sequence
    initial begin
        rst = 1; coin = 2'b00;
        #10;
        rst = 0;

        coin = 2'b01; #10;
        coin = 2'b10; #10;
        coin = 2'b01; #10;
        coin = 2'b10; #10;
        coin = 2'b10; #10;
        coin = 2'b01; #10;
        coin = 2'b10; #10;

        coin = 2'b00; #20;

        $finish;
    end

endmodule

problem3_vending/waves/vending.vcd
$date
	Sun Aug 17 23:21:47 2025
$end
$version
	Icarus Verilog
$end
$timescale
	1ps
$end
$scope module tb_vending_mealy $end
$var wire 1 ! dispense $end
$var wire 1 " chg5 $end
$var reg 1 # clk $end
$var reg 2 $ coin [1:0] $end
$var reg 1 % rst $end
$scope module dut $end
$var wire 1 # clk $end
$var wire 2 & coin [1:0] $end
$var wire 1 % rst $end
$var parameter 2 ' S0 $end
$var parameter 2 ( S10 $end
$var parameter 2 ) S15 $end
$var parameter 2 * S5 $end
$var reg 1 " chg5 $end
$var reg 1 ! dispense $end
$var reg 2 + next_state [1:0] $end
$var reg 2 , state [1:0] $end
$upscope $end
$upscope $end
$enddefinitions $end
$comment Show the parameter values. $end
$dumpall
b1 *
b11 )
b10 (
b0 '
$end
#0
$dumpvars
bx ,
b0 +
b0 &
1%
b0 $
0#
0"
0!
$end
#5000
b0 ,
1#
#10000
b1 +
0#
b1 $
b1 &
0%
#15000
b10 +
b1 ,
1#
#20000
b11 +
0#
b10 $
b10 &
#25000
1"
1!
b0 +
b11 ,
1#
#30000
0"
1!
0#
b1 $
b1 &
#35000
b1 +
0!
b0 ,
1#
#40000
b10 +
0#
b10 $
b10 &
#45000
1!
b0 +
b10 ,
1#
#50000
0#
#55000
b10 +
0!
b0 ,
1#
#60000
b1 +
0#
b1 $
b1 &
#65000
b10 +
b1 ,
1#
#70000
b11 +
0#
b10 $
b10 &
#75000
1"
1!
b0 +
b11 ,
1#
#80000
b11 +
0"
0!
0#
b0 $
b0 &
